<annotation>
	<folder>glass</folder>
	<filename>white-glass316.jpg</filename>
	<path>C:\Users\24pro\Documents\GitHub\aibuilders\object_detection\images\glass\white-glass316.jpg</path>
	<source>
		<database>Unknown</database>
	</source>
	<size>
		<width>236</width>
		<height>214</height>
		<depth>3</depth>
	</size>
	<segmented>0</segmented>
	<object>
		<name>glass</name>
		<pose>Unspecified</pose>
		<truncated>0</truncated>
		<difficult>0</difficult>
		<bndbox>
			<xmin>61</xmin>
			<ymin>8</ymin>
			<xmax>170</xmax>
			<ymax>180</ymax>
		</bndbox>
	</object>
</annotation>
